pkg_python2/__init__.py
akash_test5-0.0.1.dist-info/METADATA
akash_test5-0.0.1.dist-info/WHEEL
akash_test5-0.0.1.dist-info/license.txt
akash_test5-0.0.1.dist-info/top_level.txt
akash_test5-0.0.1.dist-info/RECORD
