Metadata-Version: 2.1
Name: akash-test5
Version: 0.0.1
Summary: adding number
Home-page: https://github.com/AkashKumarGit/
Author: Akash Kumar
Author-email: kumarakash631@gmail.com
License: UNKNOWN
Platform: UNKNOWN
Classifier: Programming Language :: Python :: 3
Classifier: License :: OSI Approved :: MIT License
Classifier: Operating System :: OS Independent
